versioner/__init__.py
versioner/__main__.py
versioner/Exceptions.py
versioner/Functions.py
versioner/Units.py
versioner/Version.py
versioner/Version.pyi
versioner_py-1.2.0.dist-info/LICENSE
versioner_py-1.2.0.dist-info/METADATA
versioner_py-1.2.0.dist-info/WHEEL
versioner_py-1.2.0.dist-info/RECORD
