Metadata-Version: 2.1
Name: versioner-py
Version: 1.2.0
Summary: A simple versioning module, with the ability to customise to any version-system.
Home-page: https://github.com/romanin-rf/versioner.py
License: MIT
Keywords: version,versioner,version-system,versioner.py,versioner-py
Author: Romanin
Author-email: semina054@gmail.com
Requires-Python: >=3.9,<4.0
Classifier: License :: OSI Approved :: MIT License
Classifier: Programming Language :: Python :: 3
Classifier: Programming Language :: Python :: 3.9
Classifier: Programming Language :: Python :: 3.10
Classifier: Programming Language :: Python :: 3.11
Requires-Dist: vbml (>=1.1.post1,<2.0)
Project-URL: Repository, https://github.com/romanin-rf/versioner.py
